spryx_http/__init__.py
spryx_http/async_client.py
spryx_http/auth_strategies.py
spryx_http/base.py
spryx_http/exceptions.py
spryx_http/logger.py
spryx_http/resource.py
spryx_http/retry.py
spryx_http/settings.py
spryx_http/sync_client.py
spryx_http/types.py
spryx_http-0.2.12.dist-info/METADATA
spryx_http-0.2.12.dist-info/WHEEL
spryx_http-0.2.12.dist-info/licenses/LICENSE
spryx_http-0.2.12.dist-info/RECORD
