Metadata-Version: 2.4
Name: spryx-http
Version: 0.2.12
Summary: A Python HTTP client library for Spryx services
Project-URL: Homepage, https://github.com/Spryx-AI/spryx-http-py
Project-URL: Bug Tracker, https://github.com/Spryx-AI/spryx-http-py/issues
Author-email: Pedro Cantidio <pedro@spryx.ai>
License: MIT License
License-File: LICENSE
Keywords: api,client,http,spryx
Classifier: Intended Audience :: Developers
Classifier: License :: OSI Approved :: MIT License
Classifier: Operating System :: OS Independent
Classifier: Programming Language :: Python :: 3
Classifier: Programming Language :: Python :: 3.11
Classifier: Programming Language :: Python :: 3.12
Classifier: Topic :: Software Development :: Libraries :: Python Modules
Requires-Python: >=3.11
Requires-Dist: httpx<0.29.0,>=0.28.1
Requires-Dist: pydantic-settings<3.0.0,>=2.9.1
Requires-Dist: pydantic<3.0.0,>=2.11.3
Requires-Dist: spryx-core<0.2.0,>=0.1.11
Provides-Extra: dev
Requires-Dist: pyright>=1.1.390; extra == 'dev'
Requires-Dist: pytest-asyncio>=0.24.0; extra == 'dev'
Requires-Dist: pytest>=8.0.0; extra == 'dev'
Requires-Dist: ruff>=0.8.0; extra == 'dev'
